xclient
