Metadata-Version: 1.1
Name: xclient
Version: 1.11
Summary: ...
Home-page: https://github.com/leiwenzheng/xclient.git
Author: Lei wenzheng
Author-email: leiwz@kaisagroup.com
License: Apache License, Version 2.0
Platform: UNKNOWN
Classifier: Development Status :: 3 - Alpha
Classifier: Environment :: Web Environment
Classifier: Intended Audience :: Developers
Classifier: Operating System :: OS Independent
Classifier: Programming Language :: Python :: 3.5
Classifier: Programming Language :: Python :: 2.7
